mercury/rl/__init__.py
mercury/rl/episodes.py
mercury/rl/rl_dataset.py
mercury/rl/rl_model_creator.py
mercury/rl/agents/__init__.py
mercury/rl/agents/conservative_ql.py
mercury/rl/agents/imitation_learning.py
mercury/rl/environment/__init__.py
mercury/rl/environment/create_env.py
mercury/rl/environment/data_generator.py
mercury/rl/environment/minari.py
mercury/rl/toy_datasets/__init__.py
mercury/rl/toy_datasets/cannon.py
mercury/rl/toy_datasets/nim.py
mercury/rl/toy_datasets/nim_supervised.py
mercury/rl/toy_datasets/word.py
mercury/rl/tutorials/create_minari_dataset_from_pandas.ipynb
mercury/rl/tutorials/algorithms_comparison/d3rly_minari_demo.ipynb
mercury/rl/tutorials/algorithms_comparison/explore.ipynb
mercury/rl/tutorials/algorithms_comparison/montecarlo.ipynb
mercury/rl/tutorials/algorithms_comparison/q_learning.ipynb
mercury/rl/tutorials/algorithms_comparison/sarsa.ipynb
mercury/rl/tutorials/algorithms_comparison/td_learning.ipynb
mercury/rl/tutorials/algorithms_comparison/utils.py
mercury/rl/tutorials/algorithms_comparison/visualize_minari.ipynb
mercury/rl/tutorials/algorithms_comparison/DRL/offline/eval.py
mercury/rl/tutorials/algorithms_comparison/DRL/offline/models.py
mercury/rl/tutorials/algorithms_comparison/DRL/offline/offline.ipynb
mercury/rl/tutorials/algorithms_comparison/DRL/offline/train.py
mercury/rl/tutorials/algorithms_comparison/DRL/offline/utils.py
mercury/rl/tutorials/algorithms_comparison/DRL/online/agents.py
mercury/rl/tutorials/algorithms_comparison/DRL/online/dqn.py
mercury/rl/tutorials/algorithms_comparison/DRL/online/dqn_tutorial.ipynb
mercury/rl/tutorials/algorithms_comparison/DRL/online/utils.py
mercury/rl/tutorials/algorithms_comparison/torchrl_demos/cql_offline.py
mercury/rl/tutorials/algorithms_comparison/torchrl_demos/torchrl_minari_demo.ipynb
mercury/rl/tutorials/algorithms_comparison/torchrl_demos/utils.py
mercury/rl/tutorials/custom_network/custom_network.ipynb
mercury_rl-0.1.0.dist-info/METADATA
mercury_rl-0.1.0.dist-info/WHEEL
mercury_rl-0.1.0.dist-info/top_level.txt
mercury_rl-0.1.0.dist-info/RECORD
