Metadata-Version: 2.4
Name: mercury-rl
Version: 0.1.0
Summary: Proof of concept of SOTA algorithms in RL
Author-email: Marcos Galletero <marcos.galletero@bbva.com>, Santiago Basaldua <santiago.basaldua@bbva.com>
Requires-Python: >=3.10
Requires-Dist: numpy<2.0.0
Requires-Dist: pandas
Requires-Dist: tensorflow
Provides-Extra: dev
Requires-Dist: pip~=20.2.4; extra == "dev"
Requires-Dist: pytest; extra == "dev"
Requires-Dist: nbmake; extra == "dev"
Requires-Dist: coverage; extra == "dev"
Requires-Dist: requirements-parser; extra == "dev"
Requires-Dist: pyyaml; extra == "dev"
Requires-Dist: d3rlpy; extra == "dev"
Requires-Dist: gym; extra == "dev"
Requires-Dist: onnx; extra == "dev"
Requires-Dist: matplotlib; extra == "dev"
Requires-Dist: mercury-viz; extra == "dev"
Requires-Dist: minari[all]; extra == "dev"
Requires-Dist: gymnasium-robotics; extra == "dev"
Requires-Dist: minigrid; extra == "dev"
Requires-Dist: torchrl; extra == "dev"
Requires-Dist: hydra-core; extra == "dev"
Provides-Extra: doc
Requires-Dist: mkdocs; extra == "doc"
Requires-Dist: mkdocstrings[python-legacy]; extra == "doc"
Requires-Dist: mkdocs-material; extra == "doc"
Requires-Dist: mkdocs-minify-plugin==0.5.0; extra == "doc"
Requires-Dist: mkdocs-exclude; extra == "doc"
Requires-Dist: nbconvert; extra == "doc"
Requires-Dist: mkdocs-static-i18n; extra == "doc"
